dora_core/__init__.py
dora_core/asset.py
dora_core/conf.py
dora_core/engine.py
dora_core/exceptions.py
dora_core/parser.py
dora_core/plugins/__init__.py
dora_core/plugins/topics/__init__.py
dora_core/plugins/volumes/__init__.py
dora_core/plugins/volumes/file.py
dora_core/render.py
dora_core/utils.py
dora_core-0.1.0.dist-info/LICENSE
dora_core-0.1.0.dist-info/METADATA
dora_core-0.1.0.dist-info/WHEEL
dora_core-0.1.0.dist-info/RECORD
