Metadata-Version: 2.1
Name: dora-core
Version: 0.1.0
Summary: Dora Core Library
License: Apache-2.0
Author: Didone
Author-email: tiago.didone@compass.uol
Requires-Python: >=3.10,<3.13
Classifier: License :: OSI Approved :: Apache Software License
Classifier: Programming Language :: Python :: 3
Classifier: Programming Language :: Python :: 3.10
Classifier: Programming Language :: Python :: 3.11
Classifier: Programming Language :: Python :: 3.12
Classifier: Topic :: Software Development :: Build Tools
Classifier: Topic :: Software Development :: Libraries :: Python Modules
Requires-Dist: dagster-pipes (>=1.9.11,<2.0.0)
Requires-Dist: jinja2 (>=3.1.5,<4.0.0)
Requires-Dist: numpy (>=2.2.1,<3.0.0)
Requires-Dist: pyarrow (>=18.1.0,<19.0.0)
Requires-Dist: pyiceberg (>=0.8.1,<0.9.0)
Requires-Dist: pyyaml (>=6.0.2,<7.0.0)
Requires-Dist: sqlglot[rs] (>=26.1.3,<27.0.0)
